aenet_gpr/__init__.py
aenet_gpr/__main__.py
aenet_gpr/inout/__init__.py
aenet_gpr/inout/inout_process.py
aenet_gpr/inout/input_parameter.py
aenet_gpr/inout/io_print.py
aenet_gpr/inout/read_input.py
aenet_gpr/src/__init__.py
aenet_gpr/src/calculator.py
aenet_gpr/src/gpr_batch.py
aenet_gpr/src/gpr_batch_internal.py
aenet_gpr/src/gpr_batch_onthefly.py
aenet_gpr/src/gpr_iterative.py
aenet_gpr/src/mace_tool.py
aenet_gpr/src/prior.py
aenet_gpr/src/prior_onthefly.py
aenet_gpr/src/pytorch_kernel.py
aenet_gpr/src/pytorch_kernel_internal.py
aenet_gpr/src/pytorch_kernel_onthefly.py
aenet_gpr/src/pytorch_kerneltypes.py
aenet_gpr/tool/__init__.py
aenet_gpr/tool/acquisition.py
aenet_gpr/tool/aidaneba.py
aenet_gpr/tool/aidmd.py
aenet_gpr/tool/aidneb.py
aenet_gpr/tool/ase_tool.py
aenet_gpr/tool/trainingset.py
aenet_gpr/util/__init__.py
aenet_gpr/util/additional_data.py
aenet_gpr/util/additional_data_internal.py
aenet_gpr/util/prepare_data.py
aenet_gpr/util/reference_data.py
aenet_gpr/util/reference_data_internal.py
aenet_gpr-3.7.7.dist-info/LICENSE
aenet_gpr-3.7.7.dist-info/METADATA
aenet_gpr-3.7.7.dist-info/WHEEL
aenet_gpr-3.7.7.dist-info/top_level.txt
aenet_gpr-3.7.7.dist-info/RECORD
