Metadata-Version: 2.1
Name: aenet-gpr
Version: 3.7.7
Summary: Atomistic simulation tools based on Gaussian Processes Regression
Home-page: https://github.com/atomisticnet/aenet-gpr
Author: In Won Yeu
Author-email: iy2185@columbia.edu
License: MPL-2.0
Keywords: machine learning,potential energy surface,aenet,data augmentation
Requires-Python: >=3
License-File: LICENSE
Requires-Dist: ase
